nbrr/__init__.py
nbrr/_version.py
nbrr/nbrr.py
nbrr-0.1.2.dist-info/LICENSE.txt
nbrr-0.1.2.dist-info/METADATA
nbrr-0.1.2.dist-info/WHEEL
nbrr-0.1.2.dist-info/entry_points.txt
nbrr-0.1.2.dist-info/top_level.txt
nbrr-0.1.2.dist-info/RECORD
