Metadata-Version: 2.1
Name: nbrr
Version: 0.1.2
Summary: Reproducible repository skeleton
Home-page: https://github.com/pyoceans/nbrr
Author: Filipe Fernandes
Author-email: ocefpaf@gmail.com
License: BSD-3-Clause
Keywords: Reproducibility,Scientific Python,Jupyter,GitHub
Platform: UNKNOWN
Classifier: Development Status :: 4 - Beta
Classifier: License :: OSI Approved :: BSD License
Classifier: Programming Language :: Python :: 3 :: Only
Classifier: Topic :: Scientific/Engineering
Requires-Dist: depfinder
Requires-Dist: easyargs
Requires-Dist: gitpython
Requires-Dist: ruamel.yaml
Provides-Extra: testing
Requires-Dist: pytest ; extra == 'testing'
